isqtools/__init__.py
isqtools/isqc_path.py
isqtools/utils.py
isqtools/backend/__init__.py
isqtools/backend/abstract_backend.py
isqtools/backend/arclight_backend.py
isqtools/backend/autograd_backend.py
isqtools/backend/aws_backend.py
isqtools/backend/hardware_backend.py
isqtools/backend/huayi_backend.py
isqtools/backend/microqiskit.py
isqtools/backend/numpy_backend.py
isqtools/backend/qcis_backend.py
isqtools/backend/qcis_backend2.py
isqtools/backend/state_vector_simulator.py
isqtools/backend/tensorflow_backend.py
isqtools/backend/tiany_backend.py
isqtools/backend/torch_backend.py
isqtools/backend/quafu_backend/__init__.py
isqtools/backend/quafu_backend/qua_task.py
isqtools/backend/quafu_backend/quafu_backend.py
isqtools/chem/__init__.py
isqtools/chem/utils.py
isqtools/circuits/__init__.py
isqtools/circuits/abstract_circuit.py
isqtools/circuits/isq_circuit.py
isqtools/circuits/str_circuit.py
isqtools/draw/__init__.py
isqtools/draw/drawer.py
isqtools/neural_networks/__init__.py
isqtools/neural_networks/neural_network.py
isqtools/neural_networks/qnn_autograd.py
isqtools/neural_networks/qnn_param_shift.py
isqtools/neural_networks/torch_layer.py
isqtools/neural_networks/torch_wrapper.py
isqtools-1.4.3.dist-info/METADATA
isqtools-1.4.3.dist-info/WHEEL
isqtools-1.4.3.dist-info/licenses/LICENSE
isqtools-1.4.3.dist-info/RECORD
