Metadata-Version: 2.4
Name: isqtools
Version: 1.4.3
Summary: python tools for isQ
Author-email: Yusheng Yang <yangys@arclightquantum.com>
License: MIT
License-File: LICENSE
Requires-Python: >=3.10
Requires-Dist: numpy
